mapper_parser/__init__.py
mapper_parser/mapper_parser.py
mapper_parser-1.1.dist-info/METADATA
mapper_parser-1.1.dist-info/WHEEL
mapper_parser-1.1.dist-info/top_level.txt
mapper_parser-1.1.dist-info/RECORD
