Metadata-Version: 2.1
Name: mapper_parser
Version: 1.1
Summary: Mybatis mapper xml file parser
Author-email: Oliver Li <441640312@qq.com>
Project-URL: Homepage, https://github.com/baikaishuipp/mapper-parser
Project-URL: Bug Tracker, https://github.com/baikaishuipp/mapper-parser/issues
Classifier: Programming Language :: Python :: 3
Classifier: License :: OSI Approved :: MIT License
Classifier: Operating System :: OS Independent
Requires-Python: >=3.0
